{"persons":[{"firstName":"lily","lastName":"cooper","address":"489 manchester st","city":"culver","zip":"97451","phone":"841-874-9845","email":"lily@email.com"},{"firstName":"eric","lastName":"cadigan","address":"951 lonetree rd","city":"culver","zip":"97451","phone":"841-874-7458","email":"gramps@email.com"},{"firstName":"tony","lastName":"cooper","address":"112 steppes pl","city":"culver","zip":"97451","phone":"841-874-6874","email":"tcoop@ymail.com"},{"firstName":"clive","lastName":"ferguson","address":"748 townings dr","city":"culver","zip":"97451","phone":"841-874-6741","email":"clivfd@ymail.com"},{"firstName":"shawna","lastName":"stelzer","address":"947 e. rose dr","city":"culver","zip":"97451","phone":"841-874-7784","email":"ssanw@email.com"},{"firstName":"jonanathan","lastName":"marrack","address":"29 15th st","city":"culver","zip":"97451","phone":"841-874-6513","email":"drk@email.com"},{"firstName":"sophia","lastName":"zemicks","address":"892 downing ct","city":"culver","zip":"97451","phone":"841-874-7878","email":"soph@email.com"},{"firstName":"zach","lastName":"zemicks","address":"892 downing ct","city":"culver","zip":"97451","phone":"841-874-7512","email":"zarc@email.com"},{"firstName":"ron","lastName":"peters","address":"112 steppes pl","city":"culver","zip":"97451","phone":"841-874-8888","email":"jpeter@email.com"},{"firstName":"brian","lastName":"stelzer","address":"947 e. rose dr","city":"culver","zip":"97451","phone":"841-874-7784","email":"bstel@email.com"},{"firstName":"kendrik","lastName":"stelzer","address":"947 e. rose dr","city":"culver","zip":"97451","phone":"841-874-7784","email":"bstel@email.com"},{"firstName":"warren","lastName":"zemicks","address":"892 downing ct","city":"culver","zip":"97451","phone":"841-874-7512","email":"ward@email.com"},{"firstName":"peter","lastName":"duncan","address":"644 gershwin cir","city":"culver","zip":"97451","phone":"841-874-6512","email":"jaboyd@email.com"},{"firstName":"foster","lastName":"shepard","address":"748 townings dr","city":"culver","zip":"97451","phone":"841-874-6544","email":"jaboyd@email.com"},{"firstName":"jamie","lastName":"peters","address":"908 73rd st","city":"culver","zip":"97451","phone":"841-874-7462","email":"jpeter@email.com"},{"firstName":"reginold","lastName":"walker","address":"908 73rd st","city":"culver","zip":"97451","phone":"841-874-8547","email":"reg@email.com"},{"firstName":"tessa","lastName":"carman","address":"834 binoc ave","city":"culver","zip":"97451","phone":"841-874-6512","email":"tenz@email.com"}],"firestations":[{"address":"29 15th st","station":2},{"address":"112 steppes pl","station":3},{"address":"112 steppes pl","station":4},{"address":"1509 culver st","station":3},{"address":"947 e. rose dr","station":1},{"address":"644 gershwin cir","station":1},{"address":"908 73rd st","station":1},{"address":"892 downing ct","station":2},{"address":"951 lonetree rd","station":2},{"address":"834 binoc ave","station":3},{"address":"748 townings dr","station":3},{"address":"489 manchester st","station":4}],"medicalrecords":[{"firstName":"lily","lastName":"cooper","birthdate":"03/06/1994","medications":[],"allergies":[]},{"firstName":"john","lastName":"boyd","birthdate":"03/06/1984","medications":["aznol:350mg","hydrapermazol:100mg"],"allergies":["nillacilan"]},{"firstName":"jacob","lastName":"boyd","birthdate":"03/06/1989","medications":["pharmacol:5000mg","terazine:10mg","noznazol:250mg"],"allergies":[]},{"firstName":"tenley","lastName":"boyd","birthdate":"02/18/2012","medications":[],"allergies":["peanut"]},{"firstName":"sophia","lastName":"zemicks","birthdate":"03/06/1988","medications":["aznol:60mg","hydrapermazol:900mg","pharmacol:5000mg","terazine:500mg"],"allergies":["peanut","shellfish","aznol"]},{"firstName":"reginold","lastName":"walker","birthdate":"08/30/1979","medications":["thradox:700mg"],"allergies":["illisoxian"]},{"firstName":"tessa","lastName":"carman","birthdate":"02/18/2012","medications":[],"allergies":[]},{"firstName":"peter","lastName":"duncan","birthdate":"09/06/2000","medications":[],"allergies":["shellfish"]},{"firstName":"jonanathan","lastName":"marrack","birthdate":"01/03/1989","medications":[],"allergies":[]},{"firstName":"kendrik","lastName":"stelzer","birthdate":"03/06/2014","medications":["noxidian:100mg","pharmacol:2500mg"],"allergies":[]},{"firstName":"jamie","lastName":"peters","birthdate":"03/06/1982","medications":[],"allergies":[]},{"firstName":"felicia","lastName":"boyd","birthdate":"01/08/1986","medications":["tetracyclaz:650mg"],"allergies":["xilliathal"]},{"firstName":"foster","lastName":"shepard","birthdate":"01/08/1980","medications":[],"allergies":[]},{"firstName":"zach","lastName":"zemicks","birthdate":"03/06/2017","medications":[],"allergies":[]},{"firstName":"shawna","lastName":"stelzer","birthdate":"07/08/1980","medications":[],"allergies":[]},{"firstName":"allison","lastName":"boyd","birthdate":"03/15/1965","medications":["aznol:200mg"],"allergies":["nillacilan"]},{"firstName":"ron","lastName":"peters","birthdate":"04/06/1965","medications":[],"allergies":[]},{"firstName":"brian","lastName":"stelzer","birthdate":"12/06/1975","medications":["ibupurin:200mg","hydrapermazol:400mg"],"allergies":["nillacilan"]},{"firstName":"clive","lastName":"ferguson","birthdate":"03/06/1994","medications":[],"allergies":[]},{"firstName":"tony","lastName":"cooper","birthdate":"03/06/1994","medications":["hydrapermazol:300mg","dodoxadin:30mg"],"allergies":["shellfish"]},{"firstName":"warren","lastName":"zemicks","birthdate":"03/06/1985","medications":[],"allergies":[]},{"firstName":"eric","lastName":"cadigan","birthdate":"08/06/1945","medications":["tradoxidine:400mg"],"allergies":[]},{"firstName":"roger","lastName":"boyd","birthdate":"09/06/2017","medications":[],"allergies":[]}]}